rl4uc/__init__.py
rl4uc/data_retrieval.py
rl4uc/dispatch.py
rl4uc/environment.py
rl4uc/helpers.py
rl4uc/processor.py
rl4uc/data/kazarlis_units_10.csv
rl4uc/data/test_data_10gen.csv
rl4uc/data/train_data_10gen.csv
rl4uc-0.1.2.dist-info/LICENSE
rl4uc-0.1.2.dist-info/METADATA
rl4uc-0.1.2.dist-info/WHEEL
rl4uc-0.1.2.dist-info/top_level.txt
rl4uc-0.1.2.dist-info/RECORD
