Metadata-Version: 2.1
Name: rl4uc
Version: 0.1.2
Summary: Reinforcement learning environment for the unit commitment problem
Author: Patrick de Mars
Author-email: pwdemars@gmail.com
Classifier: Programming Language :: Python :: 3
Classifier: License :: OSI Approved :: MIT License
Classifier: Operating System :: OS Independent
Requires-Python: >=3.6
License-File: LICENSE
Requires-Dist: numpy
Requires-Dist: pandas
